{
  "Amunnet": 899,
  "Suroned": 786,
  "Adeto Ez": 696,
  "Pepperoney": 684,
  "Toxic Adriians": 633,
  "Not Target": 614,
  "Ny Co": 557,
  "Mel Melissa": 544,
  "Violent Ends": 530,
  "Little Vinz": 502,
  "Waken": 494,
  "Thalduss": 483,
  "Garncuch Tadziik": 474,
  "Beerciq": 446,
  "Toxic Harry Barca": 441,
  "Exlifer": 425,
  "Droppzepam": 399,
  "Paladeann": 391,
  "Maly Helix": 386,
  "Mefiu The One": 383,
  "Kouthhxd": 371,
  "Quantum Arrow": 351,
  "Toxic Tonyy": 347,
  "Dymeeq": 345,
  "Xonapop": 343,
  "Boatbuilder Floki": 337,
  "Alva Treserka Smokuw": 336,
  "Chinampo Arch": 331,
  "Kuntaakinte": 330,
  "Revanne": 329,
  "Braguinha": 327,
  "Darth Wacha": 324,
  "Barahh Kamil Kiler": 324,
  "Neo druidax": 318,
  "Jelly Bean": 317,
  "Miss Imperfect": 314,
  "Notorious Carlos": 312,
  "Toxic Feeling Euforia": 310,
  "Nariga Omito": 299,
  "Arie Bombarie": 298,
  "Xoleus": 287,
  "No Target": 284,
  "Revanne Shanaction": 278,
  "Rebecca Kint": 277,
  "Levocation": 272,
  "Hambers": 272,
  "Odijan": 271,
  "Xo Buona Notte": 271,
  "Bolle Beer": 268,
  "Elanor Derpaloo": 260,
  "Petter Pittelpytt": 254,
  "Toxic Pie": 252,
  "War Fiend": 249,
  "Master Guita": 248,
  "Rat Hand": 245,
  "Xikitin": 241,
  "Kamikaze Yunus": 239,
  "Nutty Profesorek": 238,
  "Furious Jane": 235,
  "Pop Smoq": 233,
  "Faytah": 232,
  "Duraan": 232,
  "Dekhtar": 232,
  "Zab Zab": 229,
  "Lev James": 228,
  "Surron": 227,
  "Toxic Baarnaba": 223,
  "Huraganowy Arczan": 223,
  "Parcel Wesley": 222,
  "Dark Elzael": 217,
  "Incredible Dudi": 216,
  "Gorillasan": 213,
  "Sponsored by Voxram": 212,
  "Sec Uwii": 207,
  "Cravozin Charlover": 204,
  "King Hadid": 204,
  "Lee Xo Kyeong": 203,
  "Miga Mikes": 202,
  "Massito": 199,
  "Knight Psaico": 198,
  "Vito From Krakow": 197,
  "Nohand Dahlia": 194,
  "Valryos": 192,
  "Xeanu": 191,
  "Yunuzikat": 190,
  "Rikued": 189,
  "Elder Acidar": 185,
  "Don Sneaky": 183,
  "Sergeant Oak": 182,
  "Toxic Fifiq": 180,
  "Amateraxxu": 179,
  "Gregy the Headhunter": 179,
  "Dousethan Adrin": 176,
  "Morslyte": 175,
  "Vinsmoke": 175,
  "Kouthh": 174,
  "Immereicher": 174,
  "Happy Boody": 174,
  "Toxic Ascon": 171,
  "Zvensep": 169,
  "Panterinha De Fogo": 169,
  "Chernobyl Ak": 169,
  "Warchief Beelzeboss": 167,
  "Delicados": 167,
  "Intoxicated Monkey": 164,
  "Mini Persie": 162,
  "Radical Rene": 160,
  "Lestrenge": 159,
  "Ostra bestia": 159,
  "Lart Vall": 158,
  "Palean": 157,
  "Kong Ratz": 157,
  "Fasterns": 157,
  "Lion Reaper": 155,
  "Artharun Hoodz Legacy": 155,
  "Rams Vox": 153,
  "Macchu Picchu Dominando": 153,
  "Saint Of Empire": 153,
  "Johnny Pannkaka": 152,
  "Deezeet": 152,
  "Emperor Kuba": 151,
  "Canariio": 150,
  "Pekky Skywalker": 150,
  "Micolaj": 150,
  "Niewymiarowa Ukleja": 148,
  "Tilio Trona": 148,
  "Leoeloe": 147,
  "Paralyzer Ruushmaax": 145,
  "Joaninha Vasconcelos": 142,
  "Dee zetted": 142,
  "Gui on Fire": 142,
  "Dhanikat": 138,
  "Kopciuu": 138,
  "Pan pomylka": 138,
  "Kuubiq": 137,
  "Irona Anledrian": 137,
  "Evull Jack": 136,
  "Raditz Morningstar": 131,
  "Ziuv": 130,
  "Hannzz": 129,
  "Kubeeq": 129,
  "Jessica Alonso": 127,
  "Vi Torio": 126,
  "Ruufs": 126,
  "Ons Zemsta": 124,
  "Peskaiito del kaiito": 124,
  "Roffalightning": 123,
  "Ryanhender": 123,
  "Replacement Professorek": 122,
  "Ozi Al Dente": 122,
  "Nohand Pie": 120,
  "Zoxebek": 120,
  "Incun": 116,
  "Rixaari": 115,
  "Pie Softsjit": 115,
  "Contatinho Paitaon": 114,
  "Tobbz Kawi": 114,
  "Olczas Hombre": 114,
  "Dangerous Kiedosinho": 113,
  "Bandito Neversleep": 111,
  "Tony Abandonado": 110,
  "Fanatisme": 110,
  "Majestic Pudash": 110,
  "Rayroko Baylante": 109,
  "Palladyn Speed": 109,
  "Resident Scorpia": 109,
  "Jirad Maar": 107,
  "Sir Kekss": 107,
  "Dha ny": 105,
  "Dezzie": 103,
  "Akg On": 100,
  "Jacol ziom": 100,
  "Khaltonz": 100,
  "Sssdchar Vunira": 100,
  "Hardkoreta Pont Aeri": 98,
  "Delta vile": 95,
  "Karlys Star": 94,
  "Don Kwiateek Krol": 93,
  "Toxic Gilet Jaune": 93,
  "Elijah Bloodline": 93,
  "Mhaiyah": 92,
  "Ashrai": 92,
  "Huxy Hell": 92,
  "Druid Chackuoo": 91,
  "Bartosz Arabska Przygoda": 89,
  "Riiu": 89,
  "Mistrz Agamotto": 87,
  "Jonnsu": 87,
  "Pie": 87,
  "Ethereal Bolter": 86,
  "Anttor": 86,
  "Raging Joe": 85,
  "Haki Rei": 84,
  "Perlik Mastah": 83,
  "Malparit": 82,
  "Xilian": 82,
  "Maniac Matt": 81,
  "Bongostan": 81,
  "Jemey Dwa": 80,
  "Sucelluss": 80,
  "Tar get": 79,
  "Mimi'Dra": 79,
  "Magzilla": 79,
  "Legit Cherokee": 79,
  "Gregy Wonderfullkid": 78,
  "Kizzarro": 78,
  "Pe Wu De": 78,
  "Zioomal": 77,
  "Beggahh": 76,
  "Robin Kint": 76,
  "Spahst": 76,
  "Exkardam": 75,
  "Kwiateek": 75,
  "Mendeto": 75,
  "Drututt": 74,
  "Toxic Boombie": 73,
  "King Rybak": 72,
  "Alcaponek": 72,
  "Persephonie": 72,
  "Ram Vox": 72,
  "Sonec": 71,
  "Abu Sadoh": 71,
  "Madziulek": 71,
  "Santosme Fake": 71,
  "Acidaxzor": 70,
  "Itz Dramat": 70,
  "Ablivion": 70,
  "Szybka Roxa": 70,
  "Jinzar": 70,
  "Shecky": 70,
  "Sarmito": 69,
  "Lady Variatka": 69,
  "Elcocote": 69,
  "Dan Glingwang": 68,
  "Zika Bruta": 68,
  "Ruthless Codina": 68,
  "Qui Goon Jin": 68,
  "Zamknieta Lazienka": 67,
  "Champii": 67,
  "Sponsored By Ramvox": 67,
  "Skufro": 66,
  "My Little Pie": 66,
  "Zwyrodnialy cham": 65,
  "Nachos": 65,
  "Rebeld Zika": 65,
  "Edziu Posterunkowy": 65,
  "Yedlin": 65,
  "Planbb": 65,
  "Reo Light": 64,
  "Fullinquisitor": 64,
  "Aprendiz de Alquimiista": 63,
  "Kandylend": 63,
  "Fifiq": 62,
  "Susan Fero": 62,
  "Amantis Delta": 62,
  "Bendurion": 61,
  "Janki": 61,
  "Warvunir": 60,
  "Shoogunsz": 60,
  "Heaven Vzla": 60,
  "Male Zolte Sanki": 59,
  "Drakam": 58,
  "Nuke Druid": 58,
  "Alfonses": 58,
  "Softcor": 58,
  "Fariinato": 57,
  "Oscaroo": 57,
  "Reaper Axemp": 57,
  "Ruktion insane": 56,
  "Tyldi": 56,
  "Woody Heruz": 56,
  "Loony Iwan": 56,
  "Targeted": 56,
  "Almighty Armin": 55,
  "Cheeky Chimp": 55,
  "Gravy Baby": 55,
  "Dofydd": 54,
  "Retro Muu": 54,
  "Toxic Rayroko": 54,
  "Teary Babo": 54,
  "Russ Is It": 54,
  "Druid the smith": 54,
  "Deathzael": 54,
  "Toucedo Style": 54,
  "Dezzie Parafull": 54,
  "Zuiz": 54,
  "Bapstar": 54,
  "Toxic Drawciik": 53,
  "Xildao": 53,
  "He Que": 53,
  "Elrana Wunus": 52,
  "Gidiga": 52,
  "Alexst": 52,
  "Mlody Beastmode": 50,
  "Knight Wiesiek": 50,
  "Ruby Kint": 50,
  "Rektby Torgo": 49,
  "Fallriaan": 49,
  "Raging Ruktion": 49,
  "Phantom Phoenix": 49,
  "Verson": 48,
  "Full Charms Library": 48,
  "Toxic Torcik": 48,
  "Doggosaurus": 48,
  "Lobo Assassino": 48,
  "Darkaayn": 47,
  "Shur is shur": 46,
  "Qwene": 46,
  "Miichalek": 46,
  "Innundation": 46,
  "Jota Eme": 46,
  "Bode de Mizuno": 46,
  "Olir Gorja": 45,
  "Pepee": 45,
  "Chamu io": 45,
  "Angelo Mirga": 44,
  "Maffe kees": 44,
  "Bella Ktra": 43,
  "Hunteatore": 43,
  "Reiseapotheke": 43,
  "Deus Valah": 43,
  "Svampis Bob": 42,
  "Kohoj Undefiled Hobo": 42,
  "Elchico Fabuloso": 42,
  "Lanchadanan": 42,
  "Taya The Diamond": 41,
  "Mini Epus": 40,
  "Baby Wildu": 40,
  "Dreatu Eage": 40,
  "Neutrofilo": 40,
  "Claq": 40,
  "Mathz Healerz": 40,
  "Yuwiz": 39,
  "Kodimeistter": 39,
  "West Curry": 39,
  "Beast Keith": 39,
  "Sirenyus": 39,
  "Stor Jessy": 39,
  "Im Really Frisky": 38,
  "Neimerzk": 38,
  "Zloaa": 38,
  "Voaal": 38,
  "Barvis Spindelmannen": 38,
  "Thuvielle": 38,
  "Kolega Airon": 38,
  "Elder Szaleniec": 38,
  "Oneshotdruid": 37,
  "Raging Angel": 37,
  "Forest Bobii": 37,
  "Ako Mate": 37,
  "Sorcerer of Elysium": 37,
  "Sdfly Peoplecry": 36,
  "Silverflow Ez": 36,
  "Dayaanee": 36,
  "Hellwalker Russell": 36,
  "Lord Arthadan": 36,
  "Insane Tiastes": 36,
  "Miss Gigi": 35,
  "Sir Roxys Crazy": 35,
  "Paralizator Na Klate": 35,
  "Just Peti": 35,
  "Rageaz": 35,
  "Fake Ruhar": 35,
  "Elite Tajfunix": 34,
  "Fokov Hast": 34,
  "Cleey On Zeluna": 34,
  "Sathalios": 34,
  "Kohoj Kohojovic Kohojsson": 34,
  "Lothar Druid": 34,
  "Yung Sterydziarz": 34,
  "Jazz Magnetism": 34,
  "Splittin Wigz": 33,
  "Kobieta Kosa": 33,
  "Yunge": 33,
  "Baldedroid": 33,
  "Krasava": 32,
  "Toxic Kewu": 32,
  "Fille Smutt": 32,
  "Toxic Golden": 32,
  "Ataxo": 32,
  "Two Chacky": 32,
  "Baproyalstar": 32,
  "Leko Healler": 32,
  "Deathslyte": 32,
  "Pavlina": 32,
  "Miranda Fer": 32,
  "Rhedoihc": 32,
  "Itsbad Nofun": 32,
  "Ronnz": 31,
  "Beggahhowa": 31,
  "Abdoszz": 31,
  "Williamswff": 31,
  "Liion Matiias": 31,
  "Suupra": 31,
  "Cheeky Kiara": 30,
  "Norweski Kolowrotek": 30,
  "Sir Miki Colio": 30,
  "Ireneli": 30,
  "Roffanabb": 30,
  "Rookie Legend": 30,
  "Hyokh": 30,
  "Rasamaha Kuba": 30,
  "Gandalf Joe": 29,
  "Pillow Corrupted": 29,
  "Princess Eimy": 29,
  "Marky Boyo": 29,
  "Socranixzor": 29,
  "Garncuch Emaliowany": 29,
  "Niffu": 29,
  "Maciej Giertych": 28,
  "Nash Inteligencia Artificial": 28,
  "Brendejek": 28,
  "Ivvy Lottus": 27,
  "Veritalio": 27,
  "Olir Gorje": 27,
  "Kausz Bloker": 27,
  "Arth Arta": 27,
  "Elder Druid Clou": 27,
  "Hornswoggler": 27,
  "Senzu Mage": 27,
  "Change Target Guys": 27,
  "Ron back": 26,
  "Ozikowsky": 26,
  "Zii po": 26,
  "Pudash": 26,
  "Tami Dirielspe": 26,
  "Ascan Elafas": 26,
  "Ven Tranquilo": 26,
  "Qetir": 26,
  "Mana Motah": 26,
  "Klettte": 25,
  "Tiiastes": 25,
  "Tuesday": 25,
  "Don Walker": 25,
  "Sir Runuz": 25,
  "Red Rum Mikolash": 25,
  "Soul Frango": 25,
  "Ivan lizak": 25,
  "Iwedur": 25,
  "Thiastes": 24,
  "Pall Brook": 24,
  "Skulllb Ash": 24,
  "Little Phat Dan": 24,
  "Flipando Reokone": 24,
  "Toxic Damiano": 23,
  "Ujii Warface": 23,
  "Taya The Sapphire": 23,
  "Zegotinha Deboxado": 23,
  "Hercman": 23,
  "Blanksprit": 23,
  "Cumali": 23,
  "Tito Garci": 23,
  "Naboombie": 23,
  "Ghidorath": 23,
  "Special Keith": 22,
  "Eltio frescas": 22,
  "Tushy Joe": 22,
  "Lukal Fero": 22,
  "Mill Role": 22,
  "Tony No Heal": 22,
  "Czesti Sniper": 22,
  "Matira": 22,
  "Marshmalow": 22,
  "Skero": 21,
  "Lucian Asador Persistente": 21,
  "Ai Lurdes": 21,
  "Karbasek": 21,
  "Luminis Arthadan": 21,
  "Erezeteve": 21,
  "Gazowana Musztada": 20,
  "Garjak": 20,
  "Choragiewa Lutis": 20,
  "Soska": 20,
  "Fluffy Eggs": 20,
  "Arasuuhl": 20,
  "Ikesis": 20,
  "Ikkizito": 20,
  "Kryok Elia": 20,
  "Vladimir Makarov": 20,
  "Itz Anlightus": 20,
  "Earnil Killer": 19,
  "Proboszcz": 19,
  "Phekz": 19,
  "Szah Maat": 19,
  "Droidon Capone": 19,
  "Toxic Zwingly": 19,
  "Politimester Bastian": 19,
  "Cottage Pie": 19,
  "Dejw Atlar": 19,
  "Lukasz With Mustache": 18,
  "Iz Mefioo": 18,
  "Lutises": 18,
  "Ap Ed": 18,
  "Bubko Shinobi": 18,
  "Peidinho Flamenjante": 18,
  "Cabed Nearamarth": 18,
  "Kertoip Nurmegedenov": 18,
  "Daddy Purru": 18,
  "Hellwalker Profesorek": 18,
  "Legionary Sidador": 18,
  "Chempion Songo": 18,
  "Frags On Keith": 18,
  "Rayndaro Laverael": 18,
  "Pekky Khamzai": 18,
  "Not Zoxerr": 18,
  "Dangerouss Kamisek": 18,
  "Marc Heilsbringer": 17,
  "Archangel Sayrex": 17,
  "Dolcze": 17,
  "Socote Atocha": 17,
  "Miglant": 17,
  "Kyfon Ed": 17,
  "Blobbin": 17,
  "Poko Strzala": 17,
  "Elzael": 17,
  "Jigsacho": 17,
  "Natkeye Crafinbel": 17,
  "Doignus": 17,
  "Gabhriela": 16,
  "Wurgor": 16,
  "Levo Kenor": 16,
  "Dan Full Bless": 16,
  "Nieswiadomy Arbuz Chaosu": 16,
  "Frozen Bob": 16,
  "Robin Cholret": 16,
  "Simkan": 16,
  "Merediev": 16,
  "Assa Shelby": 15,
  "Toxic Surgotix": 15,
  "Kohoj of Alektorophobia": 15,
  "Helfur Sill": 15,
  "Sonqo Wargod": 15,
  "Asconic": 15,
  "Head Morgado": 15,
  "On Ly Phantoms": 15,
  "Depredatoor": 15,
  "Vincent Van Kox": 15,
  "Juuninhow": 15,
  "Rikuzx": 15,
  "Thor Viggo": 14,
  "Tyrmaras Elri": 14,
  "Galera once": 14,
  "Souter": 14,
  "Gomi Nolas": 14,
  "Rambo Renee": 14,
  "Yuri Ciloxh": 14,
  "Nice Joke": 14,
  "Crown Rudeboy": 14,
  "Furious Pedestrian": 14,
  "Elder Aernith": 14,
  "Little Raxek": 14,
  "Nagasis": 14,
  "Iva Biggen": 14,
  "Fyxy": 14,
  "Elder Monmo": 14,
  "Joker Lyan": 13,
  "Mini Shuurii": 13,
  "Crixoos": 13,
  "Magical Dan": 13,
  "Barabush": 13,
  "Simus Aeros": 13,
  "Rafaro": 13,
  "Kapi Kapi Kapi": 13,
  "Astank": 13,
  "Bolibompa Ez": 13,
  "Mini Miwily": 13,
  "Soulwar not finished": 13,
  "Frost Frajer Asura": 13,
  "Titaner": 13,
  "Neeutral": 13,
  "Noonio": 13,
  "Gaami Ed": 13,
  "Urmeline": 13,
  "Blackout the Druid": 13,
  "Mickey Mike": 12,
  "Tissaia de Vreiss": 12,
  "Weetforspeed": 12,
  "Invanes": 12,
  "Enemix": 12,
  "Biscoito Chapeleiro": 12,
  "Tavyra Shan": 12,
  "Xardas Messiah": 12,
  "Versys": 12,
  "Colonel Jack": 12,
  "Murgrian Agra": 12,
  "Clancy Wiggum": 12,
  "Ree Target": 12,
  "Cheeky Czika": 12,
  "Bad Tripz": 12,
  "Little Phat Hender": 12,
  "Matte Ragequit": 12,
  "Futerko": 12,
  "Jibbey": 12,
  "Pineapple piza": 12,
  "Neska Ovi": 12,
  "Kungfu Hansen": 12,
  "Koshim": 12,
  "Mystic Glance": 11,
  "Elmer Fudd": 11,
  "Salty Sonic": 11,
  "Magi Sita": 11,
  "Ixthar": 11,
  "Mah Sivhead": 11,
  "Senorlento": 11,
  "Herr Kat": 11,
  "Surogator": 11,
  "Trilo de slechterik": 11,
  "Elite berserker": 11,
  "Deshaa": 11,
  "Szaron": 11,
  "Sarones": 11,
  "Mattick": 11,
  "Sir Dirdok": 11,
  "Eliseok": 11,
  "Big Bearclaw": 11,
  "Insane Creatures": 11,
  "Losgeslagen Paladin": 10,
  "Elder Zakrza": 10,
  "Gando Scuorion": 10,
  "Niepamiec": 10,
  "Sarmeeto": 10,
  "Bobi Bobito": 10,
  "Ecra Lurien": 10,
  "Nafukany Koczkodan": 10,
  "Mauy Hooy": 10,
  "Arno Tufu": 10,
  "Damor Sher": 10,
  "Nightwatcherz": 10,
  "Czarujacy Krzysiu": 10,
  "Toxic Tilio": 10,
  "Koning Karel": 9,
  "Mini Anton": 9,
  "Kouthxd": 9,
  "Rambo Rene": 9,
  "Cichy Ogrodnik": 9,
  "Shimuni": 9,
  "Martinemo Energizer": 9,
  "Ghost of Kasetori": 9,
  "More Massiv Legend": 9,
  "Hazems": 9,
  "Fred De": 9,
  "Oxiigen": 9,
  "Rudzikowski": 9,
  "Vox Rams": 9,
  "Elor Gexas": 9,
  "Dengobita Psyroco": 9,
  "Souza Ravenclaw": 9,
  "Pastor Trajo": 9,
  "Flek Hek": 9,
  "Sennju Hashiramma": 9,
  "Magzic": 8,
  "Szlanki": 8,
  "Bartoszki": 8,
  "Jason Panax": 8,
  "Manquelee": 8,
  "Mini kamikaze Yunus": 8,
  "Mini Massa": 8,
  "Ajeyyy": 8,
  "Pzhugger Demzy": 8,
  "Moshtorp": 8,
  "Pyteko": 8,
  "Zoxerr": 8,
  "General Gazzman": 8,
  "Soldadita Marinera": 8,
  "Straszny Gosc": 8,
  "Mantaires": 8,
  "Fa fael": 8,
  "Billy van Kox": 8,
  "Cris Rich": 7,
  "Ezachel": 7,
  "Rakev": 7,
  "Macare": 7,
  "Mage Splass": 7,
  "Blazing Ana": 7,
  "Leo Lightning": 7,
  "Simple Ez": 7,
  "Pan rallaoo": 7,
  "Danyxz": 7,
  "Shantak": 7,
  "Kahandry": 7,
  "Bije Ueczki": 7,
  "Giorgio Menelini": 7,
  "Andro Esfinge": 7,
  "Roffa Godz": 7,
  "Gabs Darksoul": 7,
  "Toxic Danny": 7,
  "Tadis Cadeterya": 7,
  "Queen Leia": 7,
  "Elder Solin": 6,
  "Galya The Sorcerer": 6,
  "Yoyodojo": 6,
  "Insane Axell": 6,
  "Zaro The Helder": 6,
  "Dismal Mage": 6,
  "Mortrixia": 6,
  "Anty parcel": 6,
  "Magical Danitoo": 6,
  "Wexlerr": 6,
  "Parcel Diaz": 6,
  "Menina Belha": 6,
  "Tasty Jimmy": 6,
  "Thadon Rhoredoka": 6,
  "Seemia": 6,
  "Bruno the Sioher": 6,
  "Evill Chackuoo": 6,
  "Reny Sart": 6,
  "Epus": 6,
  "Agenciorek": 6,
  "Selafek": 6,
  "Parcel Revanne": 6,
  "Mehmedzik Okurek": 6,
  "Dao Stryver": 6,
  "Claqy": 6,
  "Xeqq": 6,
  "Catalonian Rudeboy": 6,
  "Goldenex": 6,
  "Euforia": 6,
  "Skurzak": 5,
  "Gost ghost": 5,
  "Rooyzz Paralyzer": 5,
  "Lilith From Hells": 5,
  "Hunnteed": 5,
  "Enanillo": 5,
  "Thanin": 5,
  "Lysy Zbrazersa": 5,
  "Roffss": 5,
  "Kubeeqq": 5,
  "Golden Bridge": 5,
  "Archmage Zed": 5,
  "Tur laad": 5,
  "Puumpam": 5,
  "Zxeresen": 5,
  "Toja Massa": 5,
  "Gia Gargaml": 5,
  "Kililimilili": 5,
  "Lokiec Pieta Typie": 5,
  "Przepukliinka": 5,
  "Darth Kaos": 5,
  "Wyindilyzuwany": 5,
  "Kryog": 5,
  "Sayannek": 5,
  "Mociek Sorc": 5,
  "Chackuoo": 5,
  "Horushus": 5,
  "Braand": 5,
  "Richard Boone": 5,
  "Tak Mocno": 5,
  "Test Propionat": 5,
  "Asto Beles": 5,
  "Ramievoh Tealiztyne": 4,
  "Lord Shephirox": 4,
  "Nohand Vinz": 4,
  "Draf Thos": 4,
  "Amazing Adry": 4,
  "Satai": 4,
  "Raila Black": 4,
  "Pawel Wielki Mag": 4,
  "Aktivver": 4,
  "Dark Morslyte": 4,
  "Johny Gumble": 4,
  "Syarabjt": 4,
  "Volm": 4,
  "Dizzle Jizzle": 4,
  "Waleff": 4,
  "Oyac": 4,
  "Awesome Requ": 4,
  "Shadow of vendetta": 4,
  "Sariyah": 4,
  "Juses Di Medici": 4,
  "Roffsaa": 4,
  "Fleeting Flipflop": 4,
  "Dark Prisma": 4,
  "Suprerah": 4,
  "Flre Devil": 4,
  "Abuzivo": 4,
  "Guma Charlover": 4,
  "Lemoniadowy Luj": 4,
  "Miwily": 4,
  "Nenmahrak": 4,
  "Muted Cop": 4,
  "Douglas": 4,
  "Deruss": 4,
  "Herox": 4,
  "Kim Kong": 4,
  "Rivux Sagor": 4,
  "Biri The Nervion": 4,
  "Alladyn Serior": 4,
  "Parcel Snikerer": 4,
  "Sacred Notsniwsz": 4,
  "Yuritomi": 4,
  "Loldor Keddon": 4,
  "Herach": 4,
  "Jan Owe Waldner": 4,
  "Zmek": 4,
  "Rudi Healer": 4,
  "Czimiczanga": 3,
  "Tebeotemato": 3,
  "Lutannilia": 3,
  "Cricke Kofot": 3,
  "Count Jerr": 3,
  "Iury Wastafull": 3,
  "Neywalker": 3,
  "Gdzie Ten Chlieb": 3,
  "Molada": 3,
  "Lill Turken": 3,
  "Pan Cucumbeer": 3,
  "Crrass": 3,
  "Daamo": 3,
  "Eowe Alax": 3,
  "Lulk kirwa": 3,
  "Matqueen": 3,
  "Sir Inxoki": 3,
  "Elanor Derpalo": 3,
  "Will Morek": 3,
  "Droide": 3,
  "Yanza Healer": 3,
  "General lovisa": 3,
  "Triggered Ryan": 3,
  "Manuel Chucha Papierochami": 3,
  "Sarodis": 3,
  "Tait Fefee": 3,
  "Humpii": 3,
  "Amnart": 3,
  "Wrachziike Simaekzl Hozmzcha": 3,
  "Agan Elferiel": 3,
  "Spocony Ambro": 3,
  "Makgot": 3,
  "Therminatorr": 3,
  "Idohra": 3,
  "Nemphias": 3,
  "Super Mosti": 3,
  "Mathias Bynens": 3,
  "Starfight": 3,
  "Lele illuminati": 3,
  "Dvdeus": 3,
  "Beliar": 3,
  "Chow is Cold": 3,
  "Sapo Relaxed": 3,
  "Jomans Hatake": 3,
  "Wolf Bandruid": 3,
  "Womangusti": 3,
  "Ares Canuto": 3,
  "Heal santa": 3,
  "Rene": 3,
  "Kwiateek Terror": 3,
  "Mini Mokoozz": 3,
  "Anthrocrus": 3,
  "Not Ma Fault": 3,
  "Rooyzz Bara Busz": 3,
  "Fiddy Darksoul": 3,
  "Mort Tarel": 3,
  "Yuura": 3,
  "Taya The Onyx": 3,
  "Aladdiin": 3,
  "Grabczyk": 3,
  "Belakerkas Sevi": 3,
  "Endrju Golota": 3,
  "Coco Majkel": 3,
  "Pomatia Helix": 3,
  "Mizzii": 3,
  "Tequs": 3,
  "Gohan Fury": 3,
  "Magisano": 3,
  "Thegms": 3,
  "Grzesio rasiak": 2,
  "Njeet": 2,
  "Ripunia": 2,
  "Winderblash": 2,
  "Vizsla": 2,
  "Sir Andresini": 2,
  "Zene Gune": 2,
  "Bommen Berend": 2,
  "Slapzor": 2,
  "Flushed Jones": 2,
  "Dead Plant": 2,
  "Taleet": 2,
  "Andres Eled": 2,
  "Ciepla Mizeria": 2,
  "Czesio Uwodziciel": 2,
  "Von Sork": 2,
  "Royal Radekx": 2,
  "Magda Szmul": 2,
  "Pancio Prime": 2,
  "Sir Gerhox": 2,
  "Elijah The Speller": 2,
  "Ownando Volkoff": 2,
  "Alcifux raftblon": 2,
  "Azahara la mala": 2,
  "Stor Schlevarn": 2,
  "Splist Direccion": 2,
  "Bill Biceps": 2,
  "Pekoski": 2,
  "Enchanted Snake": 2,
  "Popychadlo": 2,
  "Bruce Springsteenn": 2,
  "Vextoorsz": 2,
  "Kaniowski": 2,
  "Don Helmy": 2,
  "Malaguss": 2,
  "Consanthine": 2,
  "Gerhoxz": 2,
  "Andin Maria": 2,
  "Efrette Neversio": 2,
  "Bazze": 2,
  "Sezzion": 2,
  "Malpa": 2,
  "Senpai Neverforget": 2,
  "Ujii": 2,
  "Kashimuro Returns": 2,
  "Prince Ramadan": 2,
  "Dano Niel": 2,
  "Toxic Giinger": 2,
  "Przepity Leszek": 2,
  "Kratos Da Gerra": 2,
  "Xe Red": 2,
  "Aman Ceth": 2,
  "Diablikoh Rexulon": 2,
  "Hunter Of Fortune": 2,
  "Lara Sevon": 2,
  "Angerbast": 2,
  "Belved": 2,
  "Epic Hits": 2,
  "Ethylix": 2,
  "Esdie Full": 2,
  "Iyymd": 2,
  "Hood Rizardow": 2,
  "Toxic Ozi": 2,
  "Daw Eat": 2,
  "Emotminvilja": 2,
  "Arthas Proudmore": 2,
  "Warriors Adu": 2,
  "Jack Doidao Rookstayer": 2,
  "Fifiqovsky": 2,
  "Sir Katowitz": 2,
  "Impotento": 2,
  "Thaistes": 2,
  "Stipax": 2,
  "Kubason": 2,
  "Xolidarth": 2,
  "Fran cuz": 2,
  "Marco Goon": 2,
  "Szmuga": 2,
  "Sir Gottenks": 2,
  "Xemoroth": 2,
  "Royal Pox": 2,
  "Losgeslagen Knight": 2,
  "Natalie Bearskin": 2,
  "Fido": 2,
  "Nagietowicz": 2,
  "Prank Man": 2,
  "Tadzik Tadzik Tadzik": 1,
  "Lil Bob": 1,
  "Blyonax": 1,
  "Clowd Macedo": 1,
  "Bongo Wodne": 1,
  "Stanooskii": 1,
  "Aiktor": 1,
  "Rubzao": 1,
  "Roffa the king": 1,
  "Tom Dryden": 1,
  "Losgeslagen Sorcerer": 1,
  "Ishter": 1,
  "Martenimo": 1,
  "Mauricio Warmachine": 1,
  "Khayla Forest Nymph": 1,
  "Spalony Mentols": 1,
  "Raf the Healer": 1,
  "Raiserino Dongerino": 1,
  "Rine": 1,
  "Wislacki Nozownik": 1,
  "Roffaslikara": 1,
  "Orc berskerer": 1,
  "Crav": 1,
  "Rayroko": 1,
  "Damianski": 1,
  "Coffin Adept": 1,
  "Sweetheart Moon": 1,
  "Hellwalker Cavani": 1,
  "Void Walkerz": 1,
  "Alladyn Serriorek": 1,
  "Pie Damage": 1,
  "Tyran Nilu": 1,
  "Frontline Thuviel": 1,
  "King Mazik": 1,
  "Elpicu": 1,
  "Fux De Lux": 1,
  "Sirkiks": 1,
  "Legend Sheriff": 1,
  "Lord sokrat": 1,
  "Zaron Futaird": 1,
  "Legolas Greenleaft": 1,
  "Ardbeg Ten": 1,
  "Average Antica Enjoyer": 1,
  "Splist": 1,
  "Piv Pav": 1,
  "Bully Soapdropper": 1,
  "Demir Faban": 1,
  "Mister pjex": 1,
  "Carlover Damien": 1,
  "Moxel Powerhouse": 1,
  "Dacta Green": 1,
  "Gaverves": 1,
  "Radzik Zakladzik": 1,
  "Paral Push": 1,
  "Szklany Unbreakable": 1,
  "Leos Litielek": 1,
  "Awokeen": 1,
  "Yigi zimowe drasy": 1,
  "Tim Tank": 1,
  "Don Brikitiky": 1,
  "Rampage Brock": 1,
  "Oolena": 1,
  "Paczki Dla Geremka": 1,
  "Kronun Assassin": 1,
  "Magic Reiss": 1,
  "Raka to Stay": 1,
  "Merlinus Druid": 1,
  "Ajgory Wory": 1,
  "Pogromca Daniela": 1,
  "Hulk in Trance": 1,
  "Sibon Faur": 1,
  "Suszony Paladyn": 1,
  "Cura Noix": 1,
  "Wisniawfke": 1,
  "Arcylipa": 1,
  "Darth Busterbone": 1,
  "Rzullek Dominado": 1,
  "Roughnecks": 1,
  "Daahlia": 1,
  "Diler Olek": 1,
  "Ann Just": 1,
  "Danomes Chri": 1,
  "Julius Pepperwood": 1,
  "Alvowaxd": 1,
  "Secundelli": 1,
  "Congronus": 1,
  "Kalibabka Rahl": 1,
  "Primerak": 1,
  "Malczanitos": 1,
  "Bode de Havaianas": 1,
  "Giebonso": 1,
  "Voltorion": 1,
  "Nousoulwar": 1,
  "Piot Derreko": 1,
  "Dzym Ek": 1,
  "Brother Kamil": 1,
  "Jidler": 1,
  "Andrew Rusherz": 1,
  "Gladiators Pont Aeri": 1,
  "Nefertix": 1,
  "Senq Fox": 1,
  "Jaerven": 1,
  "Spanky Sorc": 1,
  "Clive the Knight": 1,
  "Flamelix": 1,
  "Ursus Knight": 1,
  "Roffa The Wise": 1,
  "Deefest": 1,
  "Dedmauss": 1,
  "Found Rowana": 1,
  "Instalater Visokog Napona": 1,
  "Pan nan panciam": 1,
  "Panixx": 1,
  "Warriors Adi": 1,
  "Suegroo": 1,
  "Eyolt": 1,
  "Maziqean": 1,
  "Beerking Kim": 1,
  "Head Oppressor": 1,
  "Capcarapcap Prime": 1,
  "Rena Chado": 1,
  "Thorstan": 1,
  "Prosis": 1,
  "Rusty Robin": 1,
  "Tank Vinz": 1,
  "Heit orzik": 1,
  "Edu on Eternia": 1,
  "Shaemasmos": 1,
  "Plankakrogen": 1,
  "Lordex ten": 1,
  "Sili Dydis": 1,
  "Saow": 1,
  "Labann": 1,
  "Ramona Cereza": 1,
  "Lord Noobious": 1,
  "Pete the Sleeper": 1,
  "Magister Procy": 1,
  "King Ilir": 1,
  "Chivero of cholo": 1,
  "Nyhx Amatullah": 1,
  "Parcel Ifty": 1,
  "Maiwand Kenora": 1,
  "Rallis": 1,
  "Hefty Hanz": 1,
  "Mojmsciciel": 1,
  "Finanxe": 1,
  "Wan dal": 1,
  "Wladczak": 1,
  "Hintz Bomba Vilao": 1,
  "Uhd": 1,
  "Pan srubon": 1,
  "Celtixx": 1,
  "Rush Def": 1,
  "Black Buck": 1,
  "Lukou": 1,
  "Paralamas Mage": 1,
  "Taragosho": 1,
  "Tomas The Creator": 1,
  "Helix Pomatia": 1,
  "Barnaba": 1,
  "Black Diamondz": 1,
  "Grmalj": 1,
  "Turbo Charger": 1,
  "Conan hipotermico": 1,
  "Roffaslikare": 1,
  "Never Kiick": 1,
  "Czaczero": 1,
  "Nattanz": 1,
  "Enda Drage": 1,
  "Zyanary": 1,
  "Redmode Morslyte": 1,
  "Pan Szympans": 1,
  "Masu Montana": 1,
  "Zigg Nall": 1,
  "Skysky": 1,
  "Winkeldief": 1,
  "Pani Barbaraa": 1,
  "Rich Jimmy": 1,
  "Przemeksior": 1,
  "Skojjar Inte": 1,
  "Chaosis": 1,
  "Cesar Filiipe": 1,
  "Wahlron": 1,
  "Cyaniite": 1,
  "Mini Zauberhaft": 1,
  "Marexa Eoren": 1,
  "Arela Tega": 1,
  "Kaly Orcus": 1,
  "Elder Rya": 1,
  "Dan Tchanabrake": 1,
  "Wanted Benq": 1,
  "Drume Farmer": 1,
  "Flam Chiquitoy": 1,
  "Bellatrix Nohands": 1,
  "Spieesz Sie Powoli": 1,
  "Paraliz Przysenny": 1,
  "Akrapovicc": 1,
  "Samael Apocalypsei": 1,
  "Bocxyto": 1,
  "Mini Kivoh": 1
}
